executionbackup/__init__.py
executionbackup/logger.py
executionbackup/main.py
executionbackup-0.0.2.dist-info/LICENSE
executionbackup-0.0.2.dist-info/METADATA
executionbackup-0.0.2.dist-info/WHEEL
executionbackup-0.0.2.dist-info/top_level.txt
executionbackup-0.0.2.dist-info/RECORD
