Metadata-Version: 2.1
Name: executionbackup
Version: 0.0.2
Summary: An Ethereum execution client switcher
Home-page: https://github.com/TennisBowling/executionbackup
Author: TennisBowling
Author-email: tennisbowling@tennisbowling.com
License: LICENSE.md
Platform: UNKNOWN
Requires-Python: >=3.7
License-File: LICENSE
Requires-Dist: aiohttp
Requires-Dist: asyncio
Requires-Dist: sanic
